pyfastsgg.cp38-win_amd64.pyd
PyFastSgg/__init__.py
PyFastSgg/schema.py
PyFastSgg/wrapper.py
PyFastSgg/utils/__init__.py
PyFastSgg/utils/basic_statistics.py
pyfastsgg-0.1.3.dist-info/LICENSE
pyfastsgg-0.1.3.dist-info/METADATA
pyfastsgg-0.1.3.dist-info/WHEEL
pyfastsgg-0.1.3.dist-info/top_level.txt
pyfastsgg-0.1.3.dist-info/RECORD
