Metadata-Version: 2.1
Name: pyfastsgg
Version: 0.1.3
Summary: Python CXX-API for FastSGG
Home-page: UNKNOWN
Author: UNKNOWN
Author-email: UNKNOWN
License: UNKNOWN
Platform: UNKNOWN
